[
    {
       "id": "old1",
       "old_Category": "Wordpress",
       "old_image": "img/work/Ai generated.jpg",
       "old_title": "Orient Freight",
       "old_description": "ORIENT FREIGHT BALIKBAYAN BOX SEA CARGO is a dependable company ",
       "old_project_involve": "<ul> <li>Web Development</li> <li>Design Implementation</li> <li>Frontend integration</li> </ul>",
       "old_project_url":"https://orientfreight.com.au/"
    },
    {
      "old_id": "old2",
      "old_Category": "wordpress",
      "old_image": "img/work/Ai generated.jpg",
      "old_title": "ITPI",
      "old_description": "Internation Travel Port inc.",
      "old_project_involve": "<ul> <li>Web Development</li> <li>Design Implementation</li> <li>Frontend integration</li> </ul>",
      "old_project_url":"#"
   },
   {
      "old_id": "old3",
      "old_Category": "wordpress",
      "old_image": "img/work/Ai generated.jpg",
      "old_title": "Meteor",
      "old_description": "Internation Travel Port inc.",
      "old_project_involve": "<ul> <li>Web Development</li> <li>Design Implementation</li> <li>Frontend integration</li> </ul>",
      "old_project_url":"#"
   }
]